odoo/addons/website_multi_theme/README.rst
odoo/addons/website_multi_theme/__init__.py
odoo/addons/website_multi_theme/__manifest__.py
odoo/addons/website_multi_theme/hooks.py
odoo/addons/website_multi_theme/menuitems.xml
odoo/addons/website_multi_theme/controllers/__init__.py
odoo/addons/website_multi_theme/controllers/main.py
odoo/addons/website_multi_theme/data/ir_module_category.xml
odoo/addons/website_multi_theme/data/themes_bootswatch.xml
odoo/addons/website_multi_theme/data/themes_default.xml
odoo/addons/website_multi_theme/data/themes_private.xml
odoo/addons/website_multi_theme/demo/pages.xml
odoo/addons/website_multi_theme/demo/themes.xml
odoo/addons/website_multi_theme/demo/website.xml
odoo/addons/website_multi_theme/i18n/af.po
odoo/addons/website_multi_theme/i18n/ar.po
odoo/addons/website_multi_theme/i18n/bg.po
odoo/addons/website_multi_theme/i18n/bs.po
odoo/addons/website_multi_theme/i18n/ca.po
odoo/addons/website_multi_theme/i18n/cs.po
odoo/addons/website_multi_theme/i18n/da.po
odoo/addons/website_multi_theme/i18n/de.po
odoo/addons/website_multi_theme/i18n/el.po
odoo/addons/website_multi_theme/i18n/el_GR.po
odoo/addons/website_multi_theme/i18n/en_GB.po
odoo/addons/website_multi_theme/i18n/es.po
odoo/addons/website_multi_theme/i18n/es_AR.po
odoo/addons/website_multi_theme/i18n/es_CL.po
odoo/addons/website_multi_theme/i18n/es_CO.po
odoo/addons/website_multi_theme/i18n/es_CR.po
odoo/addons/website_multi_theme/i18n/es_DO.po
odoo/addons/website_multi_theme/i18n/es_EC.po
odoo/addons/website_multi_theme/i18n/es_MX.po
odoo/addons/website_multi_theme/i18n/es_PE.po
odoo/addons/website_multi_theme/i18n/et.po
odoo/addons/website_multi_theme/i18n/eu.po
odoo/addons/website_multi_theme/i18n/fa.po
odoo/addons/website_multi_theme/i18n/fi.po
odoo/addons/website_multi_theme/i18n/fr.po
odoo/addons/website_multi_theme/i18n/gl.po
odoo/addons/website_multi_theme/i18n/he.po
odoo/addons/website_multi_theme/i18n/hr.po
odoo11_addon_website_multi_theme-11.0.1.6.1.dist-info/METADATA
odoo11_addon_website_multi_theme-11.0.1.6.1.dist-info/RECORD
odoo11_addon_website_multi_theme-11.0.1.6.1.dist-info/WHEEL
odoo11_addon_website_multi_theme-11.0.1.6.1.dist-info/top_level.txt
