Metadata-Version: 2.1
Name: odoo11-addon-website-multi-theme
Version: 11.0.1.6.1
Summary: Support different theme per website
Home-page: https://www.tecnativa.com
Author: Tecnativa, IT-Projects LLC, Onestein, Odoo Community Association (OCA)
Author-email: support@odoo-community.org
License: LGPL-3
Platform: UNKNOWN
Classifier: Programming Language :: Python
Classifier: Framework :: Odoo
Classifier: License :: OSI Approved :: GNU Lesser General Public License v3 (LGPLv3)
Requires-Python: >=2.7, !=3.0.*, !=3.1.*, !=3.2.*, !=3.3.*, !=3.4.*
Requires-Dist: odoo (<11.1dev,>=11.0a)
